{"version":1,"resource":"file:///c%3A/Users/mayra/Documents/9no%20Semestre/Multiparadigma/EjerciciosNoExpo/with.py","entries":[{"id":"FGz0.py","timestamp":1695911665129},{"id":"ootN.py","timestamp":1695912694127},{"id":"u1Iv.py","timestamp":1696005347518},{"id":"gDCZ.py","source":"undoRedo.source","timestamp":1696007630714},{"id":"HL1g.py","timestamp":1696007653777},{"id":"KF1t.py","timestamp":1696007673749},{"id":"KkJ1.py","timestamp":1696007730805},{"id":"oANl.py","timestamp":1696007783363},{"id":"1bro.py","timestamp":1696007991588},{"id":"3DzP.py","timestamp":1696008055789},{"id":"saVw.py","timestamp":1696008241723},{"id":"y28H.py","timestamp":1696008342513},{"id":"jo9l.py","timestamp":1696008380697},{"id":"hVxc.py","timestamp":1696008573247},{"id":"58lQ.py","timestamp":1696008623817},{"id":"Sfb2.py","timestamp":1696008707671},{"id":"xkfZ.py","timestamp":1696008737503},{"id":"MF8W.py","timestamp":1696008774843},{"id":"F6yr.py","timestamp":1696008827319},{"id":"w3Yz.py","timestamp":1696008852287},{"id":"FNyr.py","timestamp":1696009564092}]}